otter/__init__.py
otter_manager-0.0.1.dev1.dist-info/METADATA
otter_manager-0.0.1.dev1.dist-info/RECORD
otter_manager-0.0.1.dev1.dist-info/WHEEL
otter_manager-0.0.1.dev1.dist-info/top_level.txt
spip/__init__.py
spip/__main__.py
spip/cli.py
spip/logger.py
spip/python.py
